tipset/__init__.py
tipset/aws_reportportal_sum.py
tipset/aws_resource_monitor.py
tipset/html_parser.py
tipset/json_parser.py
tipset/rhcert_manager.py
tipset/rp_manager.py
tipset/tipsearch.py
tipset/cfg/aws_reportportal_sum.yaml
tipset/cfg/rhcert_manager.yaml
tipset/cfg/rhcert_manager_data.yaml
tipset/cfg/rp_manager.yaml
tipset/data/tips_data.json
tipset/docs/awscli_quick_start_with_examples.md
tipset/libs/__init__.py
tipset/libs/aws_libs.py
tipset/libs/generic_libs.py
tipset/libs/minilog.py
tipset/libs/polarion_adm.py
tipset/libs/rmt_ssh.py
tipset-0.2.7.dist-info/METADATA
tipset-0.2.7.dist-info/WHEEL
tipset-0.2.7.dist-info/entry_points.txt
tipset-0.2.7.dist-info/top_level.txt
tipset-0.2.7.dist-info/RECORD
