Metadata-Version: 2.1
Name: tipset
Version: 0.2.7
Summary: tipset is a colletion of mini tools under linux.
Home-page: https://github.com/liangxiao1/tipset
Author: Xiao Liang
Author-email: xiliang@redhat.com
License: GPLv3+
Classifier: License :: OSI Approved :: GNU General Public License v3 or later (GPLv3+)
Classifier: Programming Language :: Python :: 3
Classifier: Operating System :: POSIX
Requires-Python: >=3.6
Requires-Dist: argparse
